setup.py
authkerb/__init__.py
authkerb.egg-info/PKG-INFO
authkerb.egg-info/SOURCES.txt
authkerb.egg-info/dependency_links.txt
authkerb.egg-info/requires.txt
authkerb.egg-info/top_level.txt