Metadata-Version: 1.1
Name: authkerb
Version: 0.1
Summary: Kerberos authentication for Twisted
Home-page: https://github.com/alexeyzotov/authkerb
Author: Alexey Zotov
Author-email: alexey.zotov@gmail.com
License: MIT
Keywords: twisted kerberos authentication
Platform: UNKNOWN
Classifier: Development Status :: 4 - Beta
Classifier: Framework :: Twisted
Classifier: License :: OSI Approved :: MIT License
Classifier: Programming Language :: Python :: 2.7
Classifier: Programming Language :: Python :: 2 :: Only
Classifier: Topic :: Internet :: WWW/HTTP
